compressibleflows/__init__.py
compressibleflows/isentropic.py
compressibleflows/obshock.py
compressibleflows/prandltmeyer.py
compressibleflows/rayleigh.py
compressibleflows/shockjump.py
compressible_flows-1.0.3.dist-info/METADATA
compressible_flows-1.0.3.dist-info/WHEEL
compressible_flows-1.0.3.dist-info/RECORD
