Metadata-Version: 2.1
Name: compressible-flows
Version: 1.0.3
Summary: Compressible-flows is a library of isentropic equations used to predict shocks, expansions, nozzles, and diffusers
Author: Paht Juangphanich
Author-email: paht.juangphanich@nasa.gov
Requires-Python: >=3.9
Classifier: Programming Language :: Python :: 3
Classifier: Programming Language :: Python :: 3.9
Classifier: Programming Language :: Python :: 3.10
Classifier: Programming Language :: Python :: 3.11
Classifier: Programming Language :: Python :: 3.12
Requires-Dist: matplotlib
Requires-Dist: numpy (>2.0.0)
Requires-Dist: scipy (>1.14.0)
